<mujoco model="go2 scene">
  <include file="go2.xml" />

  <statistic center="0 0 0.1" extent="0.8" />

  <visual>
    <headlight diffuse="0.6 0.6 0.6" ambient="0.3 0.3 0.3" specular="0 0 0" />
    <rgba haze="0.15 0.25 0.35 1" />
    <global azimuth="-130" elevation="-20" />
  </visual>

  <asset>
    <texture type="skybox" builtin="gradient" rgb1="0.3 0.5 0.7" rgb2="0 0 0" width="512" height="3072" />
    <texture type="2d" name="groundplane" builtin="checker" mark="edge" rgb1="0.2 0.3 0.4" rgb2="0.1 0.2 0.3" markrgb="0.8 0.8 0.8" width="300" height="300" />
    <material name="groundplane" texture="groundplane" texuniform="true" texrepeat="5 5" reflectance="0.2" />
  <hfield name="perlin_hfield" size="1.0 0.75 0.2 0.2" file="../height_field.png" /><hfield name="image_hfield" size="1.0 1.0 0.02 0.1" file="../unitree_hfield.png" /></asset>

  <worldbody>
    <light pos="0 0 1.5" dir="0 0 -1" directional="true" />
    <geom name="floor" size="0 0 0.05" type="plane" material="groundplane" />
  <geom pos="1.5 0.0 0.1" type="box" size="0.5 0.75 0.1" quat="1.0 0.0 0.0 0.0" /><geom pos="1.5 0.0 0.25" type="cylinder" size="0.5 0.25 0.25" quat="1.0 0.0 0.0 0.0" /><geom pos="2.0 2.0 0.5" type="box" size="1.5 0.75 0.05" quat="0.9689124217106447 0.0 -0.24740395925452294 0.0" /><geom pos="1.2 4.0 0.075" type="box" size="0.1 0.75 0.075" quat="1.0 0.0 0.0 0.0" /><geom pos="1.4 4.0 0.22499999999999998" type="box" size="0.1 0.75 0.075" quat="1.0 0.0 0.0 0.0" /><geom pos="1.6 4.0 0.375" type="box" size="0.1 0.75 0.075" quat="1.0 0.0 0.0 0.0" /><geom pos="1.8 4.0 0.525" type="box" size="0.1 0.75 0.075" quat="1.0 0.0 0.0 0.0" /><geom pos="2.0 4.0 0.675" type="box" size="0.1 0.75 0.075" quat="1.0 0.0 0.0 0.0" /><geom pos="2.2 4.0 0.8250000000000001" type="box" size="0.1 0.75 0.075" quat="1.0 0.0 0.0 0.0" /><geom pos="2.4 4.0 0.9750000000000001" type="box" size="0.1 0.75 0.075" quat="1.0 0.0 0.0 0.0" /><geom pos="2.5999999999999996 4.0 1.125" type="box" size="0.1 0.75 0.075" quat="1.0 0.0 0.0 0.0" /><geom pos="2.8 4.0 1.275" type="box" size="0.1 0.75 0.075" quat="1.0 0.0 0.0 0.0" /><geom pos="3.0 4.0 1.4249999999999998" type="box" size="0.1 0.75 0.075" quat="1.0 0.0 0.0 0.0" /><geom pos="1.2 6.0 0.075" type="box" size="0.1 0.75 0.024999999999999994" quat="1.0 0.0 0.0 0.0" /><geom pos="1.4 6.0 0.22499999999999998" type="box" size="0.1 0.75 0.024999999999999994" quat="1.0 0.0 0.0 0.0" /><geom pos="1.6 6.0 0.375" type="box" size="0.1 0.75 0.024999999999999994" quat="1.0 0.0 0.0 0.0" /><geom pos="1.8 6.0 0.525" type="box" size="0.1 0.75 0.024999999999999994" quat="1.0 0.0 0.0 0.0" /><geom pos="2.0 6.0 0.675" type="box" size="0.1 0.75 0.024999999999999994" quat="1.0 0.0 0.0 0.0" /><geom pos="2.2 6.0 0.8250000000000001" type="box" size="0.1 0.75 0.024999999999999994" quat="1.0 0.0 0.0 0.0" /><geom pos="2.4 6.0 0.9750000000000001" type="box" size="0.1 0.75 0.024999999999999994" quat="1.0 0.0 0.0 0.0" /><geom pos="2.5999999999999996 6.0 1.125" type="box" size="0.1 0.75 0.024999999999999994" quat="1.0 0.0 0.0 0.0" /><geom pos="2.8 6.0 1.275" type="box" size="0.1 0.75 0.024999999999999994" quat="1.0 0.0 0.0 0.0" /><geom pos="3.0 6.0 1.4249999999999998" type="box" size="0.1 0.75 0.024999999999999994" quat="1.0 0.0 0.0 0.0" /><geom pos="-1.3049192135136178 5.237750428149434 -0.25" type="box" size="0.23633414306162268 0.26184356013612514 0.2302701894236495" quat="0.9951706621196451 0.000994881193647964 0.04401915652477011 0.08773070914226835" /><geom pos="-1.3049192135136178 5.412815251650826 -0.25" type="box" size="0.26356256245058546 0.24015149531179092 0.23630939937088222" quat="0.9984867428435714 0.039410984476050716 0.028277716441171517 0.025910797385196756" /><geom pos="-1.3049192135136178 5.579257255837561 -0.25" type="box" size="0.2706796121059668 0.23269082728232118 0.2689336138669468" quat="0.9884123884623581 -0.0730158495009132 -0.088705217013436 -0.09920191797740507" /><geom pos="-1.3049192135136178 5.767128104977909 -0.25" type="box" size="0.25545259326269143 0.250177446476972 0.2270115926952485" quat="0.9910764941729058 -0.07541731953471117 -0.06896872275169787 -0.08557409592943889" /><geom pos="-1.3049192135136178 5.930768872803183 -0.25" type="box" size="0.24780342509974077 0.24495206130180286 0.2485254797228843" quat="0.9907459631128175 0.09456158593666306 -0.09734886617159151 -0.0019342429796988005" /><geom pos="-1.3049192135136178 6.139408078963051 -0.25" type="box" size="0.26304188023051384 0.261916375649089 0.25523993549300844" quat="0.9907184160955531 0.010506458553212797 0.09687394707298565 -0.09477379762512599" /><geom pos="-1.3049192135136178 6.32819928487263 -0.25" type="box" size="0.2463939538257797 0.23095368534053734 0.26297786514341104" quat="0.9949925385821005 -0.09726626569543 -0.02238305874959843 -0.005302867585109651" /><geom pos="-1.3049192135136178 6.520767186102756 -0.25" type="box" size="0.27295994195059653 0.24383257063730548 0.2537423849391019" quat="0.9964964467945492 0.02149841003215442 -0.07012773676534309 0.040183957347407706" /><geom pos="-1.103425851543638 5.243307957593853 -0.25" type="box" size="0.23446507423832028 0.2667402010491922 0.25941011102494704" quat="0.9995965535543739 -0.014625827637850574 -0.0010300772815154018 -0.02432599903230392" /><geom pos="-1.103425851543638 5.395526636330989 -0.25" type="box" size="0.27080188514567183 0.25955455864330124 0.23732712278026283" quat="0.9920970992829375 -0.0832249202401954 -0.011259350247569591 -0.09322116324846344" /><geom pos="-1.103425851543638 5.603034277534156 -0.25" type="box" size="0.24882867457163355 0.254069220377663 0.2270206506692877" quat="0.9952483444439317 -0.02520874292453761 0.01445850859069758 -0.09293117717488662" /><geom pos="-1.103425851543638 5.805890821868845 -0.25" type="box" size="0.2494679783593367 0.2691741846133349 0.27060854360004327" quat="0.9955480998370081 -0.04149684610745531 0.07415347076663518 -0.04078302891299602" /><geom pos="-1.103425851543638 6.019359213788979 -0.25" type="box" size="0.24080521858817946 0.25128513828715504 0.25197862858193404" quat="0.9939172866683328 0.09295677165437881 0.05899063765768524 0.002751460374837804" /><geom pos="-1.103425851543638 6.180415987279037 -0.25" type="box" size="0.24840736367778277 0.2690888573644279 0.2310832903726796" quat="0.9966191087199394 -0.01811674950979806 0.05340220639584917 -0.05975232107230379" /><geom pos="-1.103425851543638 6.358928415864191 -0.25" type="box" size="0.26340286357676157 0.24573966634873426 0.2543964902893898" quat="0.9961797301406298 -0.07011878729630197 0.020752909592961753 -0.047734868476455215" /><geom pos="-1.103425851543638 6.573007130042758 -0.25" type="box" size="0.2267889644874065 0.23491525958525705 0.2640414578935885" quat="0.9959029019038724 -0.07171546407355157 0.051941031336425476 -0.018342067927838105" /><geom pos="-0.8804270022395397 5.224879293819671 -0.25" type="box" size="0.2731626503681239 0.24546008456796578 0.2561488368450099" quat="0.9972958473374309 -0.04972771896766465 -0.05373364620443205 0.0063907836268755885" /><geom pos="-0.8804270022395397 5.396256729758363 -0.25" type="box" size="0.27171634034378866 0.2736026998027958 0.23367676581137672" quat="0.991279301854039 0.05288482755662836 0.08776375733846715 -0.0828617138846968" /><geom pos="-0.8804270022395397 5.588250364365276 -0.25" type="box" size="0.26030462718005776 0.27157025646790467 0.2550426216819923" quat="0.9930999722445666 -0.066470587375422 0.09443218990877836 -0.020412438630405427" /><geom pos="-0.8804270022395397 5.836205632639372 -0.25" type="box" size="0.2279657129425785 0.22795622922134307 0.2298014959966303" quat="0.9946367673625828 0.05734586583485447 0.04089450717671511 0.0757416131656565" /><geom pos="-0.8804270022395397 6.0784864227303945 -0.25" type="box" size="0.2697354204407122 0.2669169082801401 0.2467018153326355" quat="0.9928580305340635 0.08830744417288297 -0.05266045025805999 -0.0605111848032422" /><geom pos="-0.8804270022395397 6.328047896174304 -0.25" type="box" size="0.23416617811392762 0.2507519427587516 0.23569395280929628" quat="0.9958825890199513 -0.016736289351681408 0.029557526613862687 0.08404830828830642" /><geom pos="-0.8804270022395397 6.522496916806432 -0.25" type="box" size="0.22506539699292452 0.25742383721057793 0.2501158769657036" quat="0.9941555636895183 0.06461516259855611 -0.028843028717443205 -0.08153327935231658" /><geom pos="-0.8804270022395397 6.71351206794146 -0.25" type="box" size="0.2542818041451868 0.26633382025509383 0.24417297430140888" quat="0.9973177400445022 -0.008099851384540552 -0.061866798163206525 0.038265089639356945" /><geom pos="-0.7039187393559245 5.218182041091256 -0.25" type="box" size="0.22791715764288106 0.2516843923778745 0.2723798156465267" quat="0.9941831285001469 0.07170767177531881 0.07617414776558162 0.025601094242451057" /><geom pos="-0.7039187393559245 5.373348569143433 -0.25" type="box" size="0.24624509440359474 0.26807661731281773 0.22695786036101498" quat="0.9912536046254659 0.05563731454320387 0.08929080004951295 -0.07967392028737465" /><geom pos="-0.7039187393559245 5.549606469018044 -0.25" type="box" size="0.24049867612600784 0.22601176050269764 0.2636632331888552" quat="0.9978596677100077 0.059174187238894414 0.015234660233617256 -0.023289573844438447" /><geom pos="-0.7039187393559245 5.7674164328762 -0.25" type="box" size="0.22893912290884944 0.2734995359844425 0.23543666912765548" quat="0.9907863614656373 -0.052775146238991044 -0.07856264041878613 -0.09687662981114377" /><geom pos="-0.7039187393559245 5.975168917432167 -0.25" type="box" size="0.26170853880890466 0.25382107052069786 0.2324199833985822" quat="0.991900003904155 -0.07577891608803078 -0.09354764303927725 0.04050650087648132" /><geom pos="-0.7039187393559245 6.1806919029801906 -0.25" type="box" size="0.2381882308198302 0.24039461489670388 0.23664346008630796" quat="0.9937414172352977 -0.03850111415837967 0.04364775552361369 -0.09534428833179391" /><geom pos="-0.7039187393559245 6.343874088651671 -0.25" type="box" size="0.22666248954853152 0.267476367175979 0.2617470299786668" quat="0.9958442782544006 -0.03886939652081104 0.034429246924747504 0.07481958592691379" /><geom pos="-0.7039187393559245 6.577171637190249 -0.25" type="box" size="0.24093757954501901 0.23417225811299797 0.25487585758610865" quat="0.9987008672218939 -0.024716451782613242 -0.03916615887115017 0.021252924993855473" /><geom pos="-0.5048553972054608 5.186237845145886 -0.25" type="box" size="0.2660040532282236 0.2693516523380855 0.2607433816275968" quat="0.9931421224932669 0.01144268069159631 -0.08811387600539801 0.07598509356093568" /><geom pos="-0.5048553972054608 5.394480190147045 -0.25" type="box" size="0.27336989738781176 0.26672067694884627 0.26990010207342635" quat="0.9963655897297475 -0.061359014179950565 -0.036108363707759016 -0.04676397172723111" /><geom pos="-0.5048553972054608 5.575155526657139 -0.25" type="box" size="0.23857652272007823 0.24440014894097123 0.2353831769714591" quat="0.9957807080830774 -0.0013019975968933764 -0.030534941830375792 -0.08652573917186832" /><geom pos="-0.5048553972054608 5.819267598343556 -0.25" type="box" size="0.2692253428613293 0.27106297645876526 0.2592320992392695" quat="0.9960787296454952 -0.02594811813838516 0.07615237182260333 0.03680592042980201" /><geom pos="-0.5048553972054608 6.045415358775831 -0.25" type="box" size="0.24313872207415388 0.25929742669946154 0.2732142680740123" quat="0.9991949074169619 -0.022948015829241625 0.03274355238552523 -0.0032841039395551364" /><geom pos="-0.5048553972054608 6.275752762550491 -0.25" type="box" size="0.23302886979811663 0.2692881637973388 0.25295262236900373" quat="0.9950399591251365 -0.0008664345798654123 0.04255491282874364 -0.08991000183240647" /><geom pos="-0.5048553972054608 6.479828374682105 -0.25" type="box" size="0.22718498738708207 0.2719756454487596 0.25075596781609805" quat="0.9927504110393992 0.06425654914584024 0.09734657039862277 0.029006249405918397" /><geom pos="-0.5048553972054608 6.649760232036385 -0.25" type="box" size="0.2639192360266701 0.27074195829336234 0.2623303320227373" quat="0.9973812006648177 -0.03919884532262439 -0.04922302977862062 0.03565507572832471" /><geom pos="-0.2994563360116915 5.246756054765893 -0.25" type="box" size="0.2258622274467869 0.2613483508009732 0.2601115273860804" quat="0.9930257263402907 0.09862573270737485 -0.06267670025473265 0.015636589124535936" /><geom pos="-0.2994563360116915 5.49637922972908 -0.25" type="box" size="0.2377281253509987 0.25580219286314726 0.2707584840233437" quat="0.9966048471025494 -0.06215749465569649 0.04077762683324769 -0.035389401516267995" /><geom pos="-0.2994563360116915 5.702129394482144 -0.25" type="box" size="0.23867220307197515 0.24343779706961147 0.2556823187117656" quat="0.9945368566418139 -0.05531440780360719 -0.0570982662098975 -0.06765016678604437" /><geom pos="-0.2994563360116915 5.866406779286347 -0.25" type="box" size="0.22862661311477733 0.23163764286565627 0.2353912832912066" quat="0.9920705306837445 0.08697413587172065 -0.06736116619010685 0.06077857457813625" /><geom pos="-0.2994563360116915 6.018743940429821 -0.25" type="box" size="0.24308003356261856 0.24518560884345542 0.251991142030129" quat="0.9949678656482916 -0.0482972396365731 -0.07487511970091151 0.04582618706094331" /><geom pos="-0.2994563360116915 6.207407784183756 -0.25" type="box" size="0.24898153919606444 0.26496602192231944 0.23452763146437908" quat="0.9964036708521193 -0.040363888256078506 0.04245124521726328 -0.061223957865985286" /><geom pos="-0.2994563360116915 6.3934529198446155 -0.25" type="box" size="0.2334583340202868 0.23996955985839638 0.26134453042334355" quat="0.9938109860697424 0.052176280290077336 0.09283547974449412 0.03160590835250598" /><geom pos="-0.2994563360116915 6.563015940823382 -0.25" type="box" size="0.24575210932626357 0.27346364251772604 0.22589444334241593" quat="0.9982995260779663 -0.030642294282939863 0.037398860129772414 0.032564264072431875" /><geom pos="-0.0774618478729947 5.165951872366522 -0.25" type="box" size="0.2433900769877236 0.26340265124923007 0.25639769926935474" quat="0.9986326548812737 0.030125674293958737 -0.00942920725648175 -0.04166958607458595" /><geom pos="-0.0774618478729947 5.38461829358152 -0.25" type="box" size="0.26750253905581517 0.23551602703656718 0.26130233049535967" quat="0.9939707993583405 0.09076869052788597 0.049848638510811595 -0.03603065474582148" /><geom pos="-0.0774618478729947 5.570496879536342 -0.25" type="box" size="0.26695783746550056 0.24206509027810894 0.2633197763337284" quat="0.9925305742737712 0.027381713069047242 -0.07107724188778508 0.09529599470495977" /><geom pos="-0.0774618478729947 5.794003625575858 -0.25" type="box" size="0.2559017264220954 0.2742078263786179 0.272066190647275" quat="0.9936954069896514 0.055051197207117125 0.06463310263153334 0.07322134837569913" /><geom pos="-0.0774618478729947 6.03791938326716 -0.25" type="box" size="0.23702738667781034 0.24424470387015879 0.26456681249705133" quat="0.99898933840316 0.035478457855069756 0.01829856431358722 0.020657766798572844" /><geom pos="-0.0774618478729947 6.255055184844175 -0.25" type="box" size="0.25091615232009057 0.24335499373703282 0.27404968404569385" quat="0.99606164773671 -0.046268725046694624 -0.07397531819122292 0.015749644094105446" /><geom pos="-0.0774618478729947 6.445957027913835 -0.25" type="box" size="0.27280979920183185 0.2362928903438054 0.24076882896592203" quat="0.9988445315569019 -0.001067321105724438 0.00021454315462474642 -0.04804598397124503" /><geom pos="-0.0774618478729947 6.645628520243239 -0.25" type="box" size="0.24386649311094297 0.24097585897389634 0.2741631796760378" quat="0.994034267603624 -0.0846853643332325 -0.05646221949761637 -0.03919542915797068" /><geom pos="0.12061812642255632 5.249938660815829 -0.25" type="box" size="0.24191062612795136 0.2549710788274021 0.23087227278494668" quat="0.9982917404431949 -0.007324974165699291 -0.021238597978931673 0.05393391949653142" /><geom pos="0.12061812642255632 5.450779369325212 -0.25" type="box" size="0.23246104607392742 0.2743654935492515 0.25813775920874427" quat="0.9981213236016765 -0.04050493936275788 0.03836028898707753 0.025331038030143586" /><geom pos="0.12061812642255632 5.648603084456964 -0.25" type="box" size="0.2577888361018195 0.23401676560018492 0.24165630033059618" quat="0.9944759073432894 0.023998635586449064 0.085911800558506 0.05532538050954045" /><geom pos="0.12061812642255632 5.861594064731788 -0.25" type="box" size="0.2710476833268535 0.23228398493532113 0.25050523911813627" quat="0.9955409641283641 -0.0030670385588271107 0.04026343369416277 0.08525044236836336" /><geom pos="0.12061812642255632 6.015491372499328 -0.25" type="box" size="0.25968401371975663 0.2587968646049501 0.2431113438635445" quat="0.9933741412181623 0.08027694891141032 0.07967562895531606 0.02037697679068458" /><geom pos="0.12061812642255632 6.169025146057747 -0.25" type="box" size="0.26887176559118475 0.23956428896356377 0.24211352324804258" quat="0.9945636592338974 -0.049487322074705103 -0.08502962859523859 0.03411883564997764" /><geom pos="0.12061812642255632 6.391950756053713 -0.25" type="box" size="0.2684801105825291 0.23864360229554654 0.25418593133228495" quat="0.9962527056472381 0.08346569547241488 -0.022516995190496648 -0.0026474700102159365" /><geom pos="0.12061812642255632 6.5594336975057175 -0.25" type="box" size="0.22721503042075242 0.2635142762360427 0.2685612569568653" quat="0.995743533189683 0.04287042626743309 0.08152650799513435 0.0032204280297086613" /><geom pos="0.3445776063594297 5.1710452205152055 -0.25" type="box" size="0.2414754588063423 0.23621015951949276 0.2643403543439613" quat="0.992578066396625 0.02210753753401863 0.07029159514204683 0.0967425994322338" /><geom pos="0.3445776063594297 5.351799482336084 -0.25" type="box" size="0.2412459346345828 0.2712157413238425 0.22776721400582856" quat="0.9991352675349626 0.018608275812145338 -0.02896699052577776 -0.023310141548633305" /><geom pos="0.3445776063594297 5.544984849599074 -0.25" type="box" size="0.2616596118676306 0.2379281601818738 0.24626852702680088" quat="0.9989209973615445 -0.03508108730775842 0.015365569324923929 0.026268947882311027" /><geom pos="0.3445776063594297 5.793280245430205 -0.25" type="box" size="0.2550952064141273 0.2439045582808988 0.24042562845981708" quat="0.9942792145950937 -0.040820300813262954 -0.05705718376654938 0.08054206507352722" /><geom pos="0.3445776063594297 5.948346588681291 -0.25" type="box" size="0.2569454174913464 0.2437098496634126 0.2666416378339794" quat="0.9966153998124027 0.020956336560014357 0.025848177975746334 0.07516946527734872" /><geom pos="0.3445776063594297 6.152190702627494 -0.25" type="box" size="0.25911581353394875 0.2380899756409624 0.27070245868040543" quat="0.9973226912570271 0.0582184654040101 -0.04423923742234624 0.0009745060964343169" /><geom pos="0.3445776063594297 6.375885190690292 -0.25" type="box" size="0.2696510529039052 0.2656659177206707 0.25918593154647124" quat="0.9916927617742953 -0.09806573163098774 -0.07924866409271555 -0.025460317430655972" /><geom pos="0.3445776063594297 6.566043208558326 -0.25" type="box" size="0.2403793418791915 0.2652240026353535 0.252141733154644" quat="0.993708346144528 -0.0886517444882996 0.06672835646408784 0.015228835986038459" /><geom pos="0.540716642590028 5.213508365781242 -0.25" type="box" size="0.26717348013973674 0.2424200863516386 0.22775703525963714" quat="0.994985520534995 0.05081549534790328 -0.00893163008433022 0.08568445216192502" /><geom pos="0.540716642590028 5.408814592842135 -0.25" type="box" size="0.2369321164880162 0.2709551520665481 0.2595687035073386" quat="0.9940711909747257 -0.0810580398612809 0.05640603802319609 -0.04550187163692543" /><geom pos="0.540716642590028 5.648618072744681 -0.25" type="box" size="0.23720290964407634 0.2520996364796936 0.24788277054764235" quat="0.9950326659388136 -0.08299623443521326 0.046577291476789386 -0.029192031497633292" /><geom pos="0.540716642590028 5.881123368631451 -0.25" type="box" size="0.26910525703052984 0.27388784925047427 0.24095718251023593" quat="0.994452335664236 0.06214228546300335 -0.06727558824906234 -0.05173860913402199" /><geom pos="0.540716642590028 6.040012876527859 -0.25" type="box" size="0.2726568790806811 0.2529312446266463 0.2513378645271916" quat="0.9935956085547156 -0.08874146602969978 0.053577313259343305 -0.04496877107053665" /><geom pos="0.540716642590028 6.200346058558194 -0.25" type="box" size="0.2359720179626043 0.24562844533401856 0.24487971283361423" quat="0.9979760412165873 0.04600697064126031 -0.02843092953986438 -0.0334493954441901" /><geom pos="0.540716642590028 6.36751381283274 -0.25" type="box" size="0.26127155327211055 0.22648443873864615 0.2514071865555966" quat="0.9929572126526327 -0.08910105255121566 -0.07789347361790033 0.005439029611743185" /><geom pos="0.540716642590028 6.611876503030654 -0.25" type="box" size="0.2462124286759229 0.24667903003549577 0.2322179271994292" quat="0.9972141623557683 -0.015762259530968 0.048812595172605874 -0.05415529636219542" /><geom type="hfield" hfield="perlin_hfield" pos="-0.5 4.0 0.0" quat="1.0 0.0 0.0 0.0" /><geom type="hfield" hfield="image_hfield" pos="-0.5 2.0 0.0" quat="0.7073882691671998 0.0 0.0 -0.706825181105366" /></worldbody>
</mujoco>